Tabby-0.4.0.dist-info/METADATA
Tabby-0.4.0.dist-info/RECORD
Tabby-0.4.0.dist-info/WHEEL
Tabby-0.4.0.dist-info/top_level.txt
Tabby-0.4.0.dist-info/zip-safe
tabby/__init__.py
tabby/base.py
tabby/fields.py
tabby/parser.py
tabby/schema.py
tabby/tests.py
