Metadata-Version: 2.1
Name: Tabby
Version: 0.4.0
Summary: Reads tabular data and turns it into python dicts
Home-page: http://github.com/signed0/tabby
Author: Nathan Villaescusa
Author-email: nathan@signedzero.com
License: BSD
Keywords: csv tsv tabular
Platform: UNKNOWN
Classifier: Development Status :: 3 - Alpha
Classifier: Operating System :: OS Independent
Classifier: License :: OSI Approved :: BSD License
Classifier: Intended Audience :: Developers
Classifier: Programming Language :: Python
Classifier: Programming Language :: Python :: 3
Classifier: Topic :: Software Development :: Libraries
